{"Addington": {"1": 200.0, "2": 336.0, "3": 435.0, "4": 379.0}, "Aranui/Bromley/Bexley": {"1": null, "2": null, "3": 380.0, "4": null}, "Ashburton": {"1": null, "2": 298.0, "3": 351.0, "4": 474.0}, "Avon Loop/Christchurch East": {"1": 264.0, "2": 363.0, "3": 438.0, "4": null}, "Avonhead/Yaldhurst": {"1": 137.0, "2": 356.0, "3": 434.0, "4": 433.0}, "Banks Peninsula/Selwyn": {"1": 157.0, "2": 377.0, "3": 430.0, "4": 509.0}, "Bishopdale/Papanui": {"1": 173.0, "2": 365.0, "3": 434.0, "4": 508.0}, "Burnside/Harewood": {"1": 143.0, "2": null, "3": 428.0, "4": 522.0}, "Burwood/Dallington/Avondale": {"1": null, "2": 293.0, "3": 419.0, "4": null}, "Christchurch Central/Hagley": {"1": 320.0, "2": 416.0, "3": 484.0, "4": null}, "Fendalton/Strowan/Bryndwr": {"1": 197.0, "2": 392.0, "3": 479.0, "4": 589.0}, "Halswell/Wigram": {"1": 187.0, "2": null, "3": 474.0, "4": 534.0}, "Hillmorton/Hoon Hay": {"1": null, "2": 319.0, "3": 413.0, "4": 486.0}, "Horby/Islington/Hei Hei": {"1": 136.0, "2": 347.0, "3": 416.0, "4": null}, "Ilam/Westburn": {"1": 178.0, "2": 382.0, "3": 446.0, "4": 546.0}, "Kaikoura/Hurunui": {"1": null, "2": null, "3": 331.0, "4": null}, "Linwood/Phillipstown": {"1": 229.0, "2": 316.0, "3": 390.0, "4": 424.0}, "MacKenzie/Waimate": {"1": null, "2": 249.0, "3": 301.0, "4": null}, "Marshland/Redwood": {"1": null, "2": 359.0, "3": 412.0, "4": 507.0}, "Merivale/St Albans West": {"1": 215.0, "2": 364.0, "3": 525.0, "4": 779.0}, "North Beach/New Brighton/Southshore": {"1": 160.0, "2": 348.0, "3": 390.0, "4": null}, "Rangiora/Kaiapoi": {"1": null, "2": 341.0, "3": 408.0, "4": 513.0}, "Redcliffs/Sumner": {"1": null, "2": 400.0, "3": 476.0, "4": 601.0}, "Riccarton": {"1": 188.0, "2": 368.0, "3": 446.0, "4": 516.0}, "Richmond/Avonside": {"1": 231.0, "2": 325.0, "3": 404.0, "4": null}, "Richmond/Shirley": {"1": null, "2": 369.0, "3": 412.0, "4": null}, "Rural Timaru/Temuka/Geraldine": {"1": null, "2": 336.0, "3": 332.0, "4": null}, "Rural Waimakariri": {"1": null, "2": 398.0, "3": 423.0, "4": 484.0}, "Sawyers Arms/Northcote/Belfast": {"1": null, "2": 350.0, "3": 429.0, "4": 540.0}, "Sockburn/Upper Riccarton": {"1": 179.0, "2": 348.0, "3": 440.0, "4": 514.0}, "Spreydon/Somerfield": {"1": 173.0, "2": 376.0, "3": 434.0, "4": 456.0}, "St Albans East/Edgeware": {"1": 206.0, "2": 333.0, "3": 434.0, "4": 504.0}, "St Albans North/ Mairehau": {"1": 151.0, "2": 403.0, "3": 441.0, "4": 521.0}, "St Martins/Beckenham/Huntsbury": {"1": null, "2": 362.0, "3": 457.0, "4": null}, "Styx/Parklands": {"1": null, "2": null, "3": 436.0, "4": 521.0}, "Sydenham/Waltham": {"1": 247.0, "2": 342.0, "3": 404.0, "4": 471.0}, "Timaru Township": {"1": 195.0, "2": 270.0, "3": 346.0, "4": null}, "Waitaki": {"1": null, "2": 291.0, "3": 324.0, "4": null}, "Westmorland/Cashmere/Barrington": {"1": null, "2": null, "3": 473.0, "4": 572.0}, "Woolston/Opawa": {"1": 165.0, "2": 304.0, "3": 392.0, "4": 491.0}}